itasca/__init__.py
itasca/ball/__init__.py
itasca/ball/thermal/__init__.py
itasca/ballarray/__init__.py
itasca/ballballarray/__init__.py
itasca/ballfacetarray/__init__.py
itasca/ballpebblearray/__init__.py
itasca/ballrblockarray/__init__.py
itasca/clump/__init__.py
itasca/clump/pebble/__init__.py
itasca/clump/template/__init__.py
itasca/clump/thermal/__init__.py
itasca/clump/thermal/pebble/__init__.py
itasca/clumparray/__init__.py
itasca/contact/__init__.py
itasca/dfn/__init__.py
itasca/dfn/fracture/__init__.py
itasca/dfn/inter/__init__.py
itasca/dfn/setinter/__init__.py
itasca/dfn/template/__init__.py
itasca/dfn/vertex/__init__.py
itasca/facetarray/__init__.py
itasca/fish/__init__.py
itasca/measure/__init__.py
itasca/pebblearray/__init__.py
itasca/pebblefacetarray/__init__.py
itasca/pebblepebblearray/__init__.py
itasca/pebblerblockarray/__init__.py
itasca/rblock/__init__.py
itasca/rblock/template/__init__.py
itasca/rblockarray/__init__.py
itasca/rblockfacetarray/__init__.py
itasca/rblockrblockarray/__init__.py
itasca/types.py
itasca/vertexarray/__init__.py
itasca/wall/__init__.py
itasca/wall/facet/__init__.py
itasca/wall/thermal/__init__.py
itasca/wall/thermal/facet/__init__.py
itasca/wall/vertex/__init__.py
itasca/wallarray/__init__.py
itasca_stub-1.0.19.dist-info/LICENSE
itasca_stub-1.0.19.dist-info/METADATA
itasca_stub-1.0.19.dist-info/WHEEL
itasca_stub-1.0.19.dist-info/RECORD
